algotides/__init__.py
algotides/__main__.py
algotides/constants.py
algotides/exceptions.py
algotides/serialization.py
algotides/structures.py
algotides/threadpool.py
algotides/interfaces/__init__.py
algotides/interfaces/qrc_graphics.py
algotides/interfaces/widgets.py
algotides/interfaces/about/__init__.py
algotides/interfaces/about/window.py
algotides/interfaces/about/credits/__init__.py
algotides/interfaces/about/credits/ui_window.py
algotides/interfaces/about/donate/__init__.py
algotides/interfaces/about/donate/ui_window.py
algotides/interfaces/about/info/__init__.py
algotides/interfaces/about/info/ui_window.py
algotides/interfaces/contacts/__init__.py
algotides/interfaces/contacts/entities.py
algotides/interfaces/contacts/ui_window.py
algotides/interfaces/contacts/widgets.py
algotides/interfaces/contacts/window.py
algotides/interfaces/contacts/manage/__init__.py
algotides/interfaces/contacts/manage/ui_window.py
algotides/interfaces/contacts/manage/window.py
algotides/interfaces/main/__init__.py
algotides/interfaces/main/closing_window.py
algotides/interfaces/main/ui_window.py
algotides/interfaces/main/window.py
algotides/interfaces/main/address/__init__.py
algotides/interfaces/main/address/frame.py
algotides/interfaces/main/address/ui_frame.py
algotides/interfaces/main/address/widgets.py
algotides/interfaces/main/address/balance/__init__.py
algotides/interfaces/main/address/balance/ui_window.py
algotides/interfaces/main/address/balance/window.py
algotides/interfaces/main/wallet/__init__.py
algotides/interfaces/main/wallet/entities.py
algotides/interfaces/main/wallet/frame.py
algotides/interfaces/main/wallet/ui_frame.py
algotides/interfaces/main/wallet/widgets.py
algotides/interfaces/main/wallet/newimport/__init__.py
algotides/interfaces/main/wallet/newimport/ui_window.py
algotides/interfaces/main/wallet/newimport/window.py
algotides/interfaces/main/wallet/unlock/__init__.py
algotides/interfaces/main/wallet/unlock/ui_window.py
algotides-1.0.4.dist-info/LICENSE.txt
algotides-1.0.4.dist-info/METADATA
algotides-1.0.4.dist-info/WHEEL
algotides-1.0.4.dist-info/entry_points.txt
algotides-1.0.4.dist-info/top_level.txt
algotides-1.0.4.dist-info/RECORD
