Metadata-Version: 2.1
Name: algotides
Version: 1.0.4
Summary: GUI for Algorand algod and kmd deamon
Home-page: UNKNOWN
Author: Giorgio Ciotti
Author-email: gciotti.dev@gmail.com
License: MIT
Project-URL: GitHub, https://github.com/CiottiGiorgio/algo-tides
Platform: UNKNOWN
Requires-Python: >=3.7, <4
License-File: LICENSE.txt
Requires-Dist: py-algorand-sdk (<2.0.0,>=1.4.1)
Requires-Dist: jsonpickle (<3.0.0,>=2.0.0)
Requires-Dist: PySide2 (<6.0.0,>=5.0.0)
Requires-Dist: qasync (<1.0.0,>=0.18.0)
Requires-Dist: aioify (<1.0.0,>=0.4.0)
